MANIFEST.in
README.md
setup.py
JQTT/__init__.py
JQTT/mqtt.py
JQTT/pub.py
JQTT/publisher.py
JQTT/sub.py
JQTT/sub2.py
JQTT/subscriber.py
JQTT.egg-info/PKG-INFO
JQTT.egg-info/SOURCES.txt
JQTT.egg-info/dependency_links.txt
JQTT.egg-info/not-zip-safe
JQTT.egg-info/requires.txt
JQTT.egg-info/top_level.txt