Metadata-Version: 2.1
Name: JQTT
Version: 1.1.0
Summary: Simple to use MQTT library based on the paho-mqtt package
Home-page: https://github.com/Jaimeloeuf/JQTT
Author: Jaime Loeuf
Author-email: jaimeloeuf@gmail.com
License: MIT
Keywords: MQTT pub publisher sub subscriber subscription broker client
Platform: UNKNOWN
Classifier: Development Status :: 4 - Beta
Classifier: Intended Audience :: Developers
Classifier: Environment :: Console
Classifier: License :: OSI Approved :: MIT License
Classifier: Natural Language :: English
Classifier: Programming Language :: Python :: 3.7
Classifier: Topic :: Communications
Classifier: Topic :: Utilities
